codewizard/__init__.py
codewizard/__main__.py
codewizard/cli.py
codewizard/docs.py
codewizard/errors.py
codewizard/quality.py
codewizard/snippets.py
codewizard/extensions/__init__.py
codewizard/extensions/extensions.py
tests/__init__.py
tests/test_cli.py
tests/test_snippets.py
codewizard-1.0.2.dist-info/LICENSE
codewizard-1.0.2.dist-info/METADATA
codewizard-1.0.2.dist-info/WHEEL
codewizard-1.0.2.dist-info/entry_points.txt
codewizard-1.0.2.dist-info/top_level.txt
codewizard-1.0.2.dist-info/RECORD
