Metadata-Version: 2.1
Name: codewizard
Version: 1.0.2
Summary: A powerful assistant toolkit for developers
Home-page: https://github.com/oops-aman/codewizard
Author: Aman Saurav
Author-email: amansaurav95@gmail.com
Classifier: Programming Language :: Python :: 3
Classifier: License :: OSI Approved :: MIT License
Classifier: Operating System :: OS Independent
Requires-Python: >=3.6
License-File: LICENSE
Requires-Dist: click
Requires-Dist: pyperclip
Requires-Dist: pylint
